eaopack/__init__.py
eaopack/assets.py
eaopack/assets_basic.py
eaopack/assets_plants.py
eaopack/assets_structured.py
eaopack/basic_classes.py
eaopack/io.py
eaopack/network_graphs.py
eaopack/optimization.py
eaopack/portfolio.py
eaopack/serialization.py
eaopack/stoch_lin_prog.py
eaopack-3.0.11.dist-info/METADATA
eaopack-3.0.11.dist-info/WHEEL
eaopack-3.0.11.dist-info/top_level.txt
eaopack-3.0.11.dist-info/RECORD
