Metadata-Version: 2.4
Name: eaopack
Version: 3.0.11
Summary: A Framework for Optimizing Decentralized Portfolios
Home-page: https://github.com/RIVACON/EAO
Author: RIVACON
Classifier: Programming Language :: Python :: 3
Classifier: Operating System :: OS Independent
Requires-Python: >=3.10
Requires-Dist: numpy<=2.3.3
Requires-Dist: pandas<=2.3.3
Requires-Dist: scipy<=1.16.1
Requires-Dist: openpyxl<=3.1.5
Requires-Dist: cvxpy<=1.7.2
Requires-Dist: cvxopt<=1.3.2
Requires-Dist: pyscipopt<=5.6.0
Requires-Dist: networkx<=3.5
Requires-Dist: matplotlib<=3.10.6
